remote_procedure/__init__.py
remote_procedure/router.py
remote_procedure/rabbitmq/__init__.py
remote_procedure/rabbitmq/base.py
remote_procedure/rabbitmq/client.py
remote_procedure/rabbitmq/error.py
remote_procedure/rabbitmq/pool.py
remote_procedure/rabbitmq/protocols.py
remote_procedure/rabbitmq/server.py
remote_procedure/rabbitmq/type.py
remote_procedure-1.3.2.dist-info/METADATA
remote_procedure-1.3.2.dist-info/WHEEL
remote_procedure-1.3.2.dist-info/top_level.txt
remote_procedure-1.3.2.dist-info/RECORD
