Metadata-Version: 2.1
Name: remote-procedure
Version: 1.3.2
Home-page: https://github.com/Beki95/rpc
Author: Imanji Beki
Author-email: imanjibeki@gmail.com
License: MIT
Classifier: License :: OSI Approved :: MIT License
Classifier: Programming Language :: Python
Classifier: Programming Language :: Python :: 3
Classifier: Programming Language :: Python :: 3.10
Classifier: Programming Language :: Python :: Implementation :: PyPy
Requires-Dist: aio-pika (==8.2.4)
Requires-Dist: pika (==1.3.1)
